.gitignore
.pre-commit-config.yaml
LICENSE
NOTICE
README.md
pyproject.toml
cubloaty/__init__.py
cubloaty/cli.py
cubloaty.egg-info/PKG-INFO
cubloaty.egg-info/SOURCES.txt
cubloaty.egg-info/dependency_links.txt
cubloaty.egg-info/entry_points.txt
cubloaty.egg-info/requires.txt
cubloaty.egg-info/top_level.txt