Metadata-Version: 2.4
Name: cubloaty
Version: 0.1.0b2
Summary: Analyze CUDA binary sizes in .so files - bloaty for CUDA kernels
Author: FlashInfer team
License: Apache-2.0
Project-URL: Homepage, https://github.com/flashinfer-ai/cubloaty
Classifier: Development Status :: 3 - Alpha
Classifier: Intended Audience :: Developers
Classifier: License :: OSI Approved :: Apache Software License
Classifier: Programming Language :: Python :: 3
Classifier: Programming Language :: Python :: 3.8
Classifier: Programming Language :: Python :: 3.9
Classifier: Programming Language :: Python :: 3.10
Classifier: Programming Language :: Python :: 3.11
Classifier: Topic :: Software Development :: Build Tools
Requires-Python: >=3.8
License-File: LICENSE
License-File: NOTICE
Requires-Dist: rich>=10.0.0
Dynamic: license-file
